dfmdash/__init__.py
dfmdash/cli.py
dfmdash/constants.py
dfmdash/covid19.py
dfmdash/dfm.py
dfmdash/io.py
dfmdash/processing.py
dfmdash/results.py
dfmdash/scm/scm.py
dfmdash/streamlit/Dynamic_Factor_Model.py
dfmdash/streamlit/factors.json
dfmdash/streamlit/in-progress/0_Data_Explorer.py
dfmdash/streamlit/in-progress/3_Data_Processing.py
dfmdash/streamlit/in-progress/5_SCM_Results.py
dfmdash/streamlit/old.py
dfmdash/streamlit/pages/1_Factor_Analysis.py
dfmdash/streamlit/pages/2_Comparative_Run_Analysis.py
dfmdash/streamlit/pages/4_Synthetic_Control_Model.py
dfmdash/streamlit/plots.py
dfmdash-1.0.0.dist-info/LICENSE
dfmdash-1.0.0.dist-info/METADATA
dfmdash-1.0.0.dist-info/WHEEL
dfmdash-1.0.0.dist-info/entry_points.txt
dfmdash-1.0.0.dist-info/RECORD
