Metadata-Version: 2.1
Name: dfmdash
Version: 1.0.0
Summary: Repository for Covid-19 Dynamic Factor Model
Home-page: https://github.com/jvivian/DFMDash
Author: J. Vivian, A. Cooke, J. Fitz
Author-email: fjtvivian@gmail.com
Requires-Python: >=3.9, !=2.7.*, !=3.0.*, !=3.1.*, !=3.2.*, !=3.3.*, !=3.4.*, !=3.5.*, !=3.6.*, !=3.7.*, !=3.8.*
Classifier: Programming Language :: Python :: 3
Classifier: Programming Language :: Python :: 3.9
Classifier: Programming Language :: Python :: 3.10
Classifier: Programming Language :: Python :: 3.11
Requires-Dist: anndata (>=0.10.6,<0.11.0)
Requires-Dist: arviz (>=0.17.1,<0.18.0)
Requires-Dist: decorator (>=5.1.1,<6.0.0)
Requires-Dist: fastparquet (>=2023.8.0,<2024.0.0)
Requires-Dist: matplotlib (>=3.8.1,<4.0.0)
Requires-Dist: nbclient (>=0.9.0,<0.10.0)
Requires-Dist: nbformat (>=5.9.2,<6.0.0)
Requires-Dist: openpyxl (>=3.1.2,<4.0.0)
Requires-Dist: pandas (>=2.1.1,<3.0.0)
Requires-Dist: plotly (>=5.18.0,<6.0.0)
Requires-Dist: plotly-express (>=0.4.1,<0.5.0)
Requires-Dist: pymc (>=5.10.4,<6.0.0)
Requires-Dist: pyyaml (>=6.0.1,<7.0.0)
Requires-Dist: rich (>=13.6.0,<14.0.0)
Requires-Dist: scikit-learn (>=1.3.1,<2.0.0)
Requires-Dist: seaborn (>=0.13.0,<0.14.0)
Requires-Dist: statsmodels (>=0.14.0,<0.15.0)
Requires-Dist: streamlit (>=1.28.1,<2.0.0)
Requires-Dist: syntheticcontrolmethods (>=1.1.17,<2.0.0)
Requires-Dist: typer (>=0.9.0,<0.10.0)
Requires-Dist: urllib3 (>=1.26.16,<2.0.0)
Project-URL: Documentation, https://jvivian.github.io/DFMDash/
Project-URL: Repository, https://github.com/jvivian/DFMDash
